<?xml version="1.0" encoding="utf-8"?>
<!DOCTYPE hibernate-mapping PUBLIC "-//Hibernate/Hibernate Mapping DTD 3.0//EN"
"http://hibernate.sourceforge.net/hibernate-mapping-3.0.dtd">
<!-- 
    Mapping file autogenerated by MyEclipse Persistence Tools
-->
<hibernate-mapping>
    <class name="entity.MessageWall" table="message_wall" catalog="borenzhuan">
        <id name="wallId" type="java.lang.Integer">
            <column name="wall_id" />
            <generator class="native" />
        </id>
        <many-to-one name="userInfo" class="entity.UserInfo" fetch="select">
            <column name="wall_user_id">
                <comment>用户id</comment>
            </column>
        </many-to-one>
        <property name="wallMessage" type="java.lang.String">
            <column name="wall_message" length="200">
                <comment>信息</comment>
            </column>
        </property>
        <property name="wallTime" type="java.sql.Timestamp">
            <column name="wall_time" length="19">
                <comment>弹幕时间</comment>
            </column>
        </property>
    </class>
</hibernate-mapping>
